openviduconnect
