Metadata-Version: 2.1
Name: openviduconnect
Version: 1.0.1
Summary: Wrapper to OpenVidu REST APIs
Home-page: https://github.com/amoghmadan/openviduconnect
Author: Amogh Madan
Author-email: amoghmadaan@gmail.com
License: MIT
Project-URL: Documentation, https://github.com/amoghmadan/openviduconnect
Platform: any
Classifier: Development Status :: 4 - Beta
Classifier: Intended Audience :: Developers
Classifier: License :: OSI Approved :: MIT License
Classifier: Operating System :: OS Independent
Classifier: Programming Language :: Python
Classifier: Programming Language :: Python :: 3
Classifier: Programming Language :: Python :: 3 :: Only
Classifier: Programming Language :: Python :: 3.7
Classifier: Programming Language :: Python :: 3.8
Classifier: Programming Language :: Python :: 3.9
Requires-Python: >=3.7
